gymnasium_minigrid/MiniGridEnv.py
gymnasium_minigrid/__init__.py
src/MiniGridEnv.py
src/__init__.py
gymnasium_minigrid-0.0.5.dist-info/LICENSE
gymnasium_minigrid-0.0.5.dist-info/METADATA
gymnasium_minigrid-0.0.5.dist-info/WHEEL
gymnasium_minigrid-0.0.5.dist-info/top_level.txt
gymnasium_minigrid-0.0.5.dist-info/RECORD
