Metadata-Version: 2.1
Name: gymnasium-minigrid
Version: 0.0.5
Summary: A mini grid environment for OpenAI Gym and Gymnasium
Home-page: https://github.com/lucasBertola/Minigrid
Author: Lucas Bertola
License: UNKNOWN
Platform: UNKNOWN
License-File: LICENSE
Requires-Dist: pygame (==2.1.3)
Requires-Dist: gymnasium (==0.28.1)
